oneforge/__init__.py
oneforge/client.py
oneforge/version.py
oneforge-0.1.0.dist-info/LICENSE.txt
oneforge-0.1.0.dist-info/METADATA
oneforge-0.1.0.dist-info/RECORD
oneforge-0.1.0.dist-info/WHEEL
oneforge-0.1.0.dist-info/top_level.txt
