Metadata-Version: 2.1
Name: oneforge
Version: 0.1.0
Summary: 1Forge REST API wrapper
Home-page: https://github.com/orgito/1forge-client
Author: Renato Orgito
Author-email: orgito@gmail.com
Maintainer: Renato Orgito
Maintainer-email: orgito@gmail.com
License: MIT
Project-URL: Bug Reports, https://github.com/orgito/1forge-client/issues
Project-URL: Source, https://github.com/orgito/1forge-client
Keywords: 1forge forex
Platform: UNKNOWN
Classifier: Development Status :: 4 - Beta
Classifier: Intended Audience :: Developers
Classifier: License :: OSI Approved :: MIT License
Classifier: Operating System :: OS Independent
Classifier: Programming Language :: Python :: 3.6
Classifier: Topic :: Software Development :: Libraries
Requires-Python: >=3.6
Requires-Dist: requests
